exception_with_retry/__init__.py
exception_with_retry/source.py
exception_with_retry-0.5.0.dist-info/AUTHORS.rst
exception_with_retry-0.5.0.dist-info/LICENSE.txt
exception_with_retry-0.5.0.dist-info/METADATA
exception_with_retry-0.5.0.dist-info/WHEEL
exception_with_retry-0.5.0.dist-info/top_level.txt
exception_with_retry-0.5.0.dist-info/RECORD
