Metadata-Version: 2.1
Name: exception-with-retry
Version: 0.5.0
Summary: Wait and retry calling an exception throwing method.
Home-page: https://github.com/doruirimescu/exception-with-retry/
Author: Doru Irimescu
License: MIT
Platform: any
Classifier: Development Status :: 4 - Beta
Classifier: Programming Language :: Python
License-File: LICENSE.txt
License-File: AUTHORS.rst
Requires-Dist: importlib-metadata ; python_version < "3.8"
Provides-Extra: testing
Requires-Dist: setuptools ; extra == 'testing'
Requires-Dist: pytest ; extra == 'testing'
Requires-Dist: pytest-cov ; extra == 'testing'
